fishbowlpy/__init__.py
fishbowlpy/browserdriver.py
fishbowlpy/config.py
fishbowlpy/drivertype.py
fishbowlpy/filedownloader.py
fishbowlpy/fishbowlapi.py
fishbowlpy/fishbowlclient.py
fishbowlpy/fishbowldatatypes.py
fishbowlpy/fishbowlloginmanager.py
fishbowlpy/urlmanager.py
fishbowlpy/utils/__init__.py
fishbowlpy/utils/logger.py
fishbowlpy-0.0.6.dist-info/LICENSE
fishbowlpy-0.0.6.dist-info/METADATA
fishbowlpy-0.0.6.dist-info/WHEEL
fishbowlpy-0.0.6.dist-info/top_level.txt
fishbowlpy-0.0.6.dist-info/RECORD
